{
  "name": "asteroid_cluster",
  "description": "Union of randomly perturbed spheres with carved cavities to mimic an asteroid cluster.",
  "factory": {
    "type": "asteroid_field",
    "params": {
      "count": 9,
      "radius_range": [
        0.3,
        0.9
      ],
      "spread": 2.2,
      "seed": 3401
    }
  },
  "sampling": {
    "strategy": "surface_band",
    "n_samples": 4800,
    "band_width": 0.08,
    "oversample_factor": 16,
    "with_normals": true
  },
  "metadata": {
    "category": "implicit_complex",
    "notes": "Rich topology with voids; stresses far-field sampling and guard construction."
  }
}
