{"id": "genericpath", "path": "/home/artushak/Projects/Misc/WikiProjects/Wikinews/NewsFetcherSimple/.venv/lib/python3.8/site-packages/mypy/typeshed/stdlib/2and3/genericpath.pyi", "mtime": 1612595191, "size": 803, "hash": "872042d4741d2ccc7e7e43bf7f36705c90e870c6db77059fc8027f7fe6d5df9a", "data_mtime": 1612455812, "dependencies": ["typing", "sys", "builtins", "abc"], "suppressed": [], "options": {"follow_imports_for_stubs": false, "allow_untyped_globals": false, "warn_no_return": true, "disallow_any_generics": true, "disallow_subclassing_any": true, "no_implicit_optional": true, "ignore_errors": false, "show_none_errors": true, "disallow_any_explicit": false, "disallow_untyped_defs": true, "platform": "linux", "warn_unused_ignores": true, "disallow_untyped_calls": true, "bazel": false, "strict_optional": true, "disallow_incomplete_defs": true, "disallow_any_expr": false, "check_untyped_defs": true, "follow_imports": "silent", "allow_redefinition": false, "implicit_reexport": false, "ignore_missing_imports": true, "plugins": [], "mypyc": false, "warn_return_any": true, "warn_unreachable": false, "always_true": [], "disallow_untyped_decorators": true, "strict_optional_whitelist": null, "disallow_any_decorated": false, "always_false": [], "strict_equality": true, "disallow_any_unimported": false, "local_partial_types": false}, "dep_prios": [5, 10, 5, 30], "dep_lines": [1, 2, 9, 1], "interface_hash": "27a14d7e2c6b32e5914bd45995169dee4ec8bed23fa08c008dec3daf4c6f7b8d", "version_id": "0.782", "ignore_all": true, "plugin_data": null}