{
  "openapi": "3.0.0",
  "info": {
    "title": "Douyin Api New",
    "version": "1.0.0",
    "description": "RapidAPI: nguyenmanhict-MuTUtGWD7K/douyin-api-new"
  },
  "servers": [
    {
      "url": "https://douyin-api-new.p.rapidapi.com"
    }
  ],
  "paths": {
    "/v1/social/douyin/app/user/post": {
      "post": {
        "summary": "post",
        "description": "",
        "operationId": "post",
        "parameters": [],
        "responses": {
          "200": {
            "description": "Successful response",
            "content": {
              "application/json": {
                "schema": {}
              }
            }
          }
        }
      }
    },
    "/v1/social/douyin/app/user/profile": {
      "post": {
        "summary": "profile",
        "description": "",
        "operationId": "profile",
        "parameters": [],
        "responses": {
          "200": {
            "description": "Successful response",
            "content": {
              "application/json": {
                "schema": {}
              }
            }
          }
        }
      }
    },
    "/v1/social/douyin/app/user/info": {
      "post": {
        "summary": "info",
        "description": "",
        "operationId": "info",
        "parameters": [],
        "responses": {
          "200": {
            "description": "Successful response",
            "content": {
              "application/json": {
                "schema": {}
              }
            }
          }
        }
      }
    },
    "/v1/social/douyin/app/user/follower": {
      "post": {
        "summary": "follower",
        "description": "",
        "operationId": "follower",
        "parameters": [],
        "responses": {
          "200": {
            "description": "Successful response",
            "content": {
              "application/json": {
                "schema": {}
              }
            }
          }
        }
      }
    },
    "/v1/social/douyin/web/search/hotvideolist": {
      "post": {
        "summary": "hotvideolist",
        "description": "",
        "operationId": "hotvideolist",
        "parameters": [],
        "responses": {
          "200": {
            "description": "Successful response",
            "content": {
              "application/json": {
                "schema": {}
              }
            }
          }
        }
      }
    },
    "/v1/social/douyin/web/search/susggestwords": {
      "post": {
        "summary": "susggestwords",
        "description": "",
        "operationId": "susggestwords",
        "parameters": [],
        "responses": {
          "200": {
            "description": "Successful response",
            "content": {
              "application/json": {
                "schema": {}
              }
            }
          }
        }
      }
    },
    "/v1/social/douyin/web/search/single": {
      "post": {
        "summary": "single",
        "description": "",
        "operationId": "single",
        "parameters": [],
        "responses": {
          "200": {
            "description": "Successful response",
            "content": {
              "application/json": {
                "schema": {}
              }
            }
          }
        }
      }
    },
    "/v1/social/douyin/web/search/item": {
      "post": {
        "summary": "item",
        "description": "",
        "operationId": "item",
        "parameters": [],
        "responses": {
          "200": {
            "description": "Successful response",
            "content": {
              "application/json": {
                "schema": {}
              }
            }
          }
        }
      }
    },
    "/v1/social/douyin/web/search/sug": {
      "post": {
        "summary": "sug",
        "description": "",
        "operationId": "sug",
        "parameters": [],
        "responses": {
          "200": {
            "description": "Successful response",
            "content": {
              "application/json": {
                "schema": {}
              }
            }
          }
        }
      }
    },
    "/v1/social/douyin/web/aweme/related": {
      "post": {
        "summary": "related",
        "description": "",
        "operationId": "related",
        "parameters": [],
        "responses": {
          "200": {
            "description": "Successful response",
            "content": {
              "application/json": {
                "schema": {}
              }
            }
          }
        }
      }
    },
    "/v1/social/douyin/web/aweme/post": {
      "post": {
        "summary": "post",
        "description": "",
        "operationId": "post_1",
        "parameters": [],
        "responses": {
          "200": {
            "description": "Successful response",
            "content": {
              "application/json": {
                "schema": {}
              }
            }
          }
        }
      }
    },
    "/v1/social/douyin/web/aweme/detailurl": {
      "post": {
        "summary": "detailUrl",
        "description": "",
        "operationId": "detailurl",
        "parameters": [],
        "responses": {
          "200": {
            "description": "Successful response",
            "content": {
              "application/json": {
                "schema": {}
              }
            }
          }
        }
      }
    },
    "/v1/social/douyin/web/aweme/detail": {
      "post": {
        "summary": "detail",
        "description": "",
        "operationId": "detail",
        "parameters": [],
        "responses": {
          "200": {
            "description": "Successful response",
            "content": {
              "application/json": {
                "schema": {}
              }
            }
          }
        }
      }
    },
    "/v1/social/douyin/app/search/poi": {
      "post": {
        "summary": "poi",
        "description": "",
        "operationId": "poi",
        "parameters": [],
        "responses": {
          "200": {
            "description": "Successful response",
            "content": {
              "application/json": {
                "schema": {}
              }
            }
          }
        }
      }
    },
    "/v1/social/douyin/app/aweme/detail_id": {
      "post": {
        "summary": "detailId",
        "description": "",
        "operationId": "detailid",
        "parameters": [],
        "responses": {
          "200": {
            "description": "Successful response",
            "content": {
              "application/json": {
                "schema": {}
              }
            }
          }
        }
      }
    },
    "/v1/social/douyin/web/feed/channel": {
      "post": {
        "summary": "channel",
        "description": "",
        "operationId": "channel",
        "parameters": [],
        "responses": {
          "200": {
            "description": "Successful response",
            "content": {
              "application/json": {
                "schema": {}
              }
            }
          }
        }
      }
    },
    "/v1/social/douyin/app/comment/list": {
      "post": {
        "summary": "list",
        "description": "",
        "operationId": "list",
        "parameters": [],
        "responses": {
          "200": {
            "description": "Successful response",
            "content": {
              "application/json": {
                "schema": {}
              }
            }
          }
        }
      }
    },
    "/v1/social/douyin/web/other/long_video_meta": {
      "get": {
        "summary": "longVideoMeta",
        "description": "",
        "operationId": "longvideometa",
        "parameters": [
          {
            "name": "episode_id_current",
            "in": "query",
            "required": false,
            "description": "Example value: ",
            "schema": {
              "type": "string",
              "default": null,
              "enum": null
            }
          },
          {
            "name": "album_id",
            "in": "query",
            "required": false,
            "description": "Example value: 7316087737772147251",
            "schema": {
              "type": "number",
              "default": "7316087737772148000",
              "enum": null
            }
          },
          {
            "name": "aweme_id_current",
            "in": "query",
            "required": false,
            "description": "Example value: ",
            "schema": {
              "type": "string",
              "default": null,
              "enum": null
            }
          }
        ],
        "responses": {
          "200": {
            "description": "Successful response",
            "content": {
              "application/json": {
                "schema": {}
              }
            }
          }
        }
      }
    },
    "/v1/social/douyin/web/search/live": {
      "post": {
        "summary": "hotList",
        "description": "",
        "operationId": "hotlist",
        "parameters": [],
        "responses": {
          "200": {
            "description": "Successful response",
            "content": {
              "application/json": {
                "schema": {}
              }
            }
          }
        }
      }
    },
    "/v1/social/douyin/app/comment/listreply": {
      "post": {
        "summary": "reply",
        "description": "",
        "operationId": "reply",
        "parameters": [],
        "responses": {
          "200": {
            "description": "Successful response",
            "content": {
              "application/json": {
                "schema": {}
              }
            }
          }
        }
      }
    },
    "/v1/social/douyin/app/search/discover": {
      "post": {
        "summary": "discover",
        "description": "",
        "operationId": "discover",
        "parameters": [],
        "responses": {
          "200": {
            "description": "Successful response",
            "content": {
              "application/json": {
                "schema": {}
              }
            }
          }
        }
      }
    },
    "/v1/social/douyin/app/mix/list": {
      "post": {
        "summary": "list",
        "description": "",
        "operationId": "list_1",
        "parameters": [],
        "responses": {
          "200": {
            "description": "Successful response",
            "content": {
              "application/json": {
                "schema": {}
              }
            }
          }
        }
      }
    },
    "/v1/social/douyin/web/other/getPcBanner": {
      "get": {
        "summary": "getPcBanner",
        "description": "",
        "operationId": "getpcbanner",
        "parameters": [],
        "responses": {
          "200": {
            "description": "Successful response",
            "content": {
              "application/json": {
                "schema": {}
              }
            }
          }
        }
      }
    },
    "/v1/social/douyin/app/hot/brand_weekly_list": {
      "post": {
        "summary": "brandWeeklyList",
        "description": "",
        "operationId": "brandweeklylist",
        "parameters": [],
        "responses": {
          "200": {
            "description": "Successful response",
            "content": {
              "application/json": {
                "schema": {}
              }
            }
          }
        }
      }
    },
    "/v1/social/douyin/app/search/single": {
      "post": {
        "summary": "single",
        "description": "",
        "operationId": "single_1",
        "parameters": [],
        "responses": {
          "200": {
            "description": "Successful response",
            "content": {
              "application/json": {
                "schema": {}
              }
            }
          }
        }
      }
    },
    "/v1/social/douyin/web/other/seo_keyword_related": {
      "get": {
        "summary": "seoKeywordRelated",
        "description": "",
        "operationId": "seokeywordrelated",
        "parameters": [
          {
            "name": "id",
            "in": "query",
            "required": false,
            "description": "Example value: 6984256064577441061",
            "schema": {
              "type": "number",
              "default": "6984256064577441000",
              "enum": null
            }
          }
        ],
        "responses": {
          "200": {
            "description": "Successful response",
            "content": {
              "application/json": {
                "schema": {}
              }
            }
          }
        }
      }
    },
    "/v1/social/douyin/app/user/following": {
      "post": {
        "summary": "following",
        "description": "",
        "operationId": "following",
        "parameters": [],
        "responses": {
          "200": {
            "description": "Successful response",
            "content": {
              "application/json": {
                "schema": {}
              }
            }
          }
        }
      }
    },
    "/v1/social/douyin/app/poi/city": {
      "get": {
        "summary": "city",
        "description": "",
        "operationId": "city",
        "parameters": [],
        "responses": {
          "200": {
            "description": "Successful response",
            "content": {
              "application/json": {
                "schema": {}
              }
            }
          }
        }
      }
    },
    "/v1/social/douyin/app/music/aweme": {
      "post": {
        "summary": "aweme",
        "description": "",
        "operationId": "aweme",
        "parameters": [],
        "responses": {
          "200": {
            "description": "Successful response",
            "content": {
              "application/json": {
                "schema": {}
              }
            }
          }
        }
      }
    },
    "/v1/social/douyin/web/other/web_shorten": {
      "get": {
        "summary": "webShorten",
        "description": "",
        "operationId": "webshorten",
        "parameters": [],
        "responses": {
          "200": {
            "description": "Successful response",
            "content": {
              "application/json": {
                "schema": {}
              }
            }
          }
        }
      }
    },
    "/v1/social/douyin/web/other/emoji_list": {
      "get": {
        "summary": "emojiList",
        "description": "",
        "operationId": "emojilist",
        "parameters": [],
        "responses": {
          "200": {
            "description": "Successful response",
            "content": {
              "application/json": {
                "schema": {}
              }
            }
          }
        }
      }
    },
    "/v1/social/douyin/app/music/chart": {
      "post": {
        "summary": "chart",
        "description": "",
        "operationId": "chart",
        "parameters": [],
        "responses": {
          "200": {
            "description": "Successful response",
            "content": {
              "application/json": {
                "schema": {}
              }
            }
          }
        }
      }
    },
    "/v1/social/douyin/app/challenge/aweme": {
      "post": {
        "summary": "aweme",
        "description": "",
        "operationId": "aweme_1",
        "parameters": [],
        "responses": {
          "200": {
            "description": "Successful response",
            "content": {
              "application/json": {
                "schema": {}
              }
            }
          }
        }
      }
    },
    "/v1/social/douyin/app/search/music": {
      "post": {
        "summary": "music",
        "description": "",
        "operationId": "music",
        "parameters": [],
        "responses": {
          "200": {
            "description": "Successful response",
            "content": {
              "application/json": {
                "schema": {}
              }
            }
          }
        }
      }
    },
    "/v1/social/douyin/app/search/challenge": {
      "post": {
        "summary": "challenge",
        "description": "",
        "operationId": "challenge",
        "parameters": [],
        "responses": {
          "200": {
            "description": "Successful response",
            "content": {
              "application/json": {
                "schema": {}
              }
            }
          }
        }
      }
    },
    "/v1/social/douyin/app/feed/index": {
      "get": {
        "summary": "index",
        "description": "",
        "operationId": "index",
        "parameters": [
          {
            "name": "max_cursor",
            "in": "query",
            "required": false,
            "description": "Example value: 0",
            "schema": {
              "type": "number",
              "default": "0",
              "enum": null
            }
          }
        ],
        "responses": {
          "200": {
            "description": "Successful response",
            "content": {
              "application/json": {
                "schema": {}
              }
            }
          }
        }
      }
    },
    "/v1/social/douyin/app/search/item": {
      "post": {
        "summary": "item",
        "description": "",
        "operationId": "item_1",
        "parameters": [],
        "responses": {
          "200": {
            "description": "Successful response",
            "content": {
              "application/json": {
                "schema": {}
              }
            }
          }
        }
      }
    },
    "/v1/social/douyin/web/feed/wallpaper": {
      "post": {
        "summary": "wallpaper",
        "description": "",
        "operationId": "wallpaper",
        "parameters": [],
        "responses": {
          "200": {
            "description": "Successful response",
            "content": {
              "application/json": {
                "schema": {}
              }
            }
          }
        }
      }
    },
    "/v1/social/douyin/app/hot/brand_billboard": {
      "post": {
        "summary": "brandBillboard",
        "description": "",
        "operationId": "brandbillboard",
        "parameters": [],
        "responses": {
          "200": {
            "description": "Successful response",
            "content": {
              "application/json": {
                "schema": {}
              }
            }
          }
        }
      }
    },
    "/v1/social/douyin/web/feed/medium_related": {
      "post": {
        "summary": "mediumRelated",
        "description": "",
        "operationId": "mediumrelated",
        "parameters": [],
        "responses": {
          "200": {
            "description": "Successful response",
            "content": {
              "application/json": {
                "schema": {}
              }
            }
          }
        }
      }
    },
    "/v1/social/douyin/app/feed/nearby": {
      "get": {
        "summary": "nearby",
        "description": "",
        "operationId": "nearby",
        "parameters": [
          {
            "name": "max_cursor",
            "in": "query",
            "required": false,
            "description": "Example value: 3",
            "schema": {
              "type": "number",
              "default": "3",
              "enum": null
            }
          },
          {
            "name": "city",
            "in": "query",
            "required": false,
            "description": "Example value: 8616124",
            "schema": {
              "type": "number",
              "default": "8616124",
              "enum": null
            }
          }
        ],
        "responses": {
          "200": {
            "description": "Successful response",
            "content": {
              "application/json": {
                "schema": {}
              }
            }
          }
        }
      }
    },
    "/v1/social/douyin/web/feed/tab": {
      "post": {
        "summary": "tab",
        "description": "",
        "operationId": "tab",
        "parameters": [],
        "responses": {
          "200": {
            "description": "Successful response",
            "content": {
              "application/json": {
                "schema": {}
              }
            }
          }
        }
      }
    },
    "/v1/social/douyin/web/feed/lvideo_theater": {
      "post": {
        "summary": "lvideoTheater",
        "description": "",
        "operationId": "lvideotheater",
        "parameters": [],
        "responses": {
          "200": {
            "description": "Successful response",
            "content": {
              "application/json": {
                "schema": {}
              }
            }
          }
        }
      }
    },
    "/v1/social/douyin/web/feed/follow": {
      "post": {
        "summary": "follow",
        "description": "",
        "operationId": "follow",
        "parameters": [],
        "responses": {
          "200": {
            "description": "Successful response",
            "content": {
              "application/json": {
                "schema": {}
              }
            }
          }
        }
      }
    },
    "/v1/social/douyin/app/poi/detail": {
      "post": {
        "summary": "detail",
        "description": "",
        "operationId": "detail_1",
        "parameters": [],
        "responses": {
          "200": {
            "description": "Successful response",
            "content": {
              "application/json": {
                "schema": {}
              }
            }
          }
        }
      }
    },
    "/v1/social/douyin/app/challenge/detail": {
      "post": {
        "summary": "detail",
        "description": "",
        "operationId": "detail_2",
        "parameters": [],
        "responses": {
          "200": {
            "description": "Successful response",
            "content": {
              "application/json": {
                "schema": {}
              }
            }
          }
        }
      }
    },
    "/v1/social/douyin/web/feed/module": {
      "post": {
        "summary": "module",
        "description": "",
        "operationId": "module",
        "parameters": [],
        "responses": {
          "200": {
            "description": "Successful response",
            "content": {
              "application/json": {
                "schema": {}
              }
            }
          }
        }
      }
    },
    "/v1/social/douyin/app/hot/search_list": {
      "get": {
        "summary": "searchList",
        "description": "",
        "operationId": "searchlist",
        "parameters": [
          {
            "name": "detail_list",
            "in": "query",
            "required": false,
            "description": "Example value: 1",
            "schema": {
              "type": "number",
              "default": "1",
              "enum": null
            }
          }
        ],
        "responses": {
          "200": {
            "description": "Successful response",
            "content": {
              "application/json": {
                "schema": {}
              }
            }
          }
        }
      }
    },
    "/v1/social/douyin/web/other/appoint_live_list": {
      "get": {
        "summary": "appointLiveList",
        "description": "",
        "operationId": "appointlivelist",
        "parameters": [],
        "responses": {
          "200": {
            "description": "Successful response",
            "content": {
              "application/json": {
                "schema": {}
              }
            }
          }
        }
      }
    },
    "/v1/social/douyin/web/other/query_account_type": {
      "get": {
        "summary": "queryAccountType",
        "description": "",
        "operationId": "queryaccounttype",
        "parameters": [
          {
            "name": "sec_user_id",
            "in": "query",
            "required": false,
            "description": "Example value: MS4wLjABAAAAIqOcUlkHRYn3R9QrxuXwCrQbarxTKLqYNDByv_hGbGU",
            "schema": {
              "type": "string",
              "default": null,
              "enum": null
            }
          }
        ],
        "responses": {
          "200": {
            "description": "Successful response",
            "content": {
              "application/json": {
                "schema": {}
              }
            }
          }
        }
      }
    },
    "/v1/social/douyin/app/poi/aweme": {
      "post": {
        "summary": "aweme",
        "description": "",
        "operationId": "aweme_2",
        "parameters": [],
        "responses": {
          "200": {
            "description": "Successful response",
            "content": {
              "application/json": {
                "schema": {}
              }
            }
          }
        }
      }
    },
    "/v1/social/douyin/app/shorten/index": {
      "post": {
        "summary": "index",
        "description": "",
        "operationId": "index_1",
        "parameters": [],
        "responses": {
          "200": {
            "description": "Successful response",
            "content": {
              "application/json": {
                "schema": {}
              }
            }
          }
        }
      }
    },
    "/v1/social/douyin/app/schema/trans": {
      "post": {
        "summary": "trans",
        "description": "",
        "operationId": "trans",
        "parameters": [],
        "responses": {
          "200": {
            "description": "Successful response",
            "content": {
              "application/json": {
                "schema": {}
              }
            }
          }
        }
      }
    },
    "/v1/social/douyin/app/search/live": {
      "post": {
        "summary": "live",
        "description": "",
        "operationId": "live",
        "parameters": [],
        "responses": {
          "200": {
            "description": "Successful response",
            "content": {
              "application/json": {
                "schema": {}
              }
            }
          }
        }
      }
    },
    "/v1/social/douyin/app/search/sug": {
      "get": {
        "summary": "sug",
        "description": "",
        "operationId": "sug_1",
        "parameters": [
          {
            "name": "keyword",
            "in": "query",
            "required": false,
            "description": "Example value: anime",
            "schema": {
              "type": "string",
              "default": null,
              "enum": null
            }
          }
        ],
        "responses": {
          "200": {
            "description": "Successful response",
            "content": {
              "application/json": {
                "schema": {}
              }
            }
          }
        }
      }
    },
    "/v1/social/douyin/app/feed/poi": {
      "get": {
        "summary": "poi",
        "description": "",
        "operationId": "poi_1",
        "parameters": [
          {
            "name": "id",
            "in": "query",
            "required": false,
            "description": "Example value: 6601124549775853572",
            "schema": {
              "type": "number",
              "default": "6601124549775854000",
              "enum": null
            }
          },
          {
            "name": "cursor",
            "in": "query",
            "required": false,
            "description": "Example value: 0",
            "schema": {
              "type": "number",
              "default": "0",
              "enum": null
            }
          },
          {
            "name": "count",
            "in": "query",
            "required": false,
            "description": "Example value: 10",
            "schema": {
              "type": "number",
              "default": "10",
              "enum": null
            }
          }
        ],
        "responses": {
          "200": {
            "description": "Successful response",
            "content": {
              "application/json": {
                "schema": {}
              }
            }
          }
        }
      }
    },
    "/v1/social/douyin/web/comment/listreply": {
      "post": {
        "summary": "reply",
        "description": "",
        "operationId": "reply_1",
        "parameters": [],
        "responses": {
          "200": {
            "description": "Successful response",
            "content": {
              "application/json": {
                "schema": {}
              }
            }
          }
        }
      }
    },
    "/v1/social/douyin/web/comment/list": {
      "post": {
        "summary": "list",
        "description": "",
        "operationId": "list_2",
        "parameters": [],
        "responses": {
          "200": {
            "description": "Successful response",
            "content": {
              "application/json": {
                "schema": {}
              }
            }
          }
        }
      }
    },
    "/v1/social/douyin/web/search/social": {
      "post": {
        "summary": "social",
        "description": "",
        "operationId": "social",
        "parameters": [],
        "responses": {
          "200": {
            "description": "Successful response",
            "content": {
              "application/json": {
                "schema": {}
              }
            }
          }
        }
      }
    },
    "/v1/social/douyin/web/mix/recommend": {
      "post": {
        "summary": "recommend",
        "description": "",
        "operationId": "recommend",
        "parameters": [],
        "responses": {
          "200": {
            "description": "Successful response",
            "content": {
              "application/json": {
                "schema": {}
              }
            }
          }
        }
      }
    },
    "/v1/social/douyin/web/mix/detail": {
      "post": {
        "summary": "detail",
        "description": "",
        "operationId": "detail_3",
        "parameters": [],
        "responses": {
          "200": {
            "description": "Successful response",
            "content": {
              "application/json": {
                "schema": {}
              }
            }
          }
        }
      }
    },
    "/v1/social/douyin/web/mix/list": {
      "post": {
        "summary": "list",
        "description": "",
        "operationId": "list_3",
        "parameters": [],
        "responses": {
          "200": {
            "description": "Successful response",
            "content": {
              "application/json": {
                "schema": {}
              }
            }
          }
        }
      }
    },
    "/v1/social/douyin/web/search/ab": {
      "post": {
        "summary": "ab",
        "description": "",
        "operationId": "ab",
        "parameters": [],
        "responses": {
          "200": {
            "description": "Successful response",
            "content": {
              "application/json": {
                "schema": {}
              }
            }
          }
        }
      }
    },
    "/v1/social/douyin/web/mix/aweme": {
      "post": {
        "summary": "aweme",
        "description": "",
        "operationId": "aweme_3",
        "parameters": [],
        "responses": {
          "200": {
            "description": "Successful response",
            "content": {
              "application/json": {
                "schema": {}
              }
            }
          }
        }
      }
    },
    "/v1/social/douyin/app/hot/brand_category": {
      "get": {
        "summary": "brandCategory",
        "description": "",
        "operationId": "brandcategory",
        "parameters": [],
        "responses": {
          "200": {
            "description": "Successful response",
            "content": {
              "application/json": {
                "schema": {}
              }
            }
          }
        }
      }
    },
    "/v1/social/douyin/web/music/aweme": {
      "post": {
        "summary": "aweme",
        "description": "",
        "operationId": "aweme_4",
        "parameters": [],
        "responses": {
          "200": {
            "description": "Successful response",
            "content": {
              "application/json": {
                "schema": {}
              }
            }
          }
        }
      }
    },
    "/v1/social/douyin/web/user/detail": {
      "post": {
        "summary": "detail",
        "description": "",
        "operationId": "detail_4",
        "parameters": [],
        "responses": {
          "200": {
            "description": "Successful response",
            "content": {
              "application/json": {
                "schema": {}
              }
            }
          }
        }
      }
    },
    "/v1/social/douyin/app/aweme/favorite": {
      "post": {
        "summary": "favorite",
        "description": "",
        "operationId": "favorite",
        "parameters": [],
        "responses": {
          "200": {
            "description": "Successful response",
            "content": {
              "application/json": {
                "schema": {}
              }
            }
          }
        }
      }
    },
    "/v1/social/douyin/app/aweme/detail_url": {
      "post": {
        "summary": "detailUrl",
        "description": "",
        "operationId": "detailurl_1",
        "parameters": [],
        "responses": {
          "200": {
            "description": "Successful response",
            "content": {
              "application/json": {
                "schema": {}
              }
            }
          }
        }
      }
    },
    "/v1/social/douyin/app/hot/search_video_list": {
      "post": {
        "summary": "searchVideoList",
        "description": "",
        "operationId": "searchvideolist",
        "parameters": [],
        "responses": {
          "200": {
            "description": "Successful response",
            "content": {
              "application/json": {
                "schema": {}
              }
            }
          }
        }
      }
    },
    "/v1/social/douyin/app/hot/billboard_aweme": {
      "get": {
        "summary": "billboardAweme",
        "description": "",
        "operationId": "billboardaweme",
        "parameters": [],
        "responses": {
          "200": {
            "description": "Successful response",
            "content": {
              "application/json": {
                "schema": {}
              }
            }
          }
        }
      }
    },
    "/v1/social/douyin/web/music/detail": {
      "post": {
        "summary": "detail",
        "description": "",
        "operationId": "detail_5",
        "parameters": [],
        "responses": {
          "200": {
            "description": "Successful response",
            "content": {
              "application/json": {
                "schema": {}
              }
            }
          }
        }
      }
    },
    "/v1/social/douyin/app/mix/aweme": {
      "post": {
        "summary": "aweme",
        "description": "",
        "operationId": "aweme_5",
        "parameters": [],
        "responses": {
          "200": {
            "description": "Successful response",
            "content": {
              "application/json": {
                "schema": {}
              }
            }
          }
        }
      }
    },
    "/v1/social/douyin/web/user/self": {
      "post": {
        "summary": "self",
        "description": "",
        "operationId": "self",
        "parameters": [],
        "responses": {
          "200": {
            "description": "Successful response",
            "content": {
              "application/json": {
                "schema": {}
              }
            }
          }
        }
      }
    },
    "/v1/social/douyin/app/hashtag/index": {
      "get": {
        "summary": "index",
        "description": "",
        "operationId": "index_2",
        "parameters": [
          {
            "name": "id",
            "in": "query",
            "required": false,
            "description": "Example value: 7023579918135008293",
            "schema": {
              "type": "number",
              "default": "7023579918135008000",
              "enum": null
            }
          },
          {
            "name": "offset",
            "in": "query",
            "required": false,
            "description": "Example value: 0",
            "schema": {
              "type": "number",
              "default": "0",
              "enum": null
            }
          },
          {
            "name": "limit",
            "in": "query",
            "required": false,
            "description": "Example value: 20",
            "schema": {
              "type": "number",
              "default": "20",
              "enum": null
            }
          }
        ],
        "responses": {
          "200": {
            "description": "Successful response",
            "content": {
              "application/json": {
                "schema": {}
              }
            }
          }
        }
      }
    },
    "/v1/social/douyin/app/mix/detail": {
      "post": {
        "summary": "detail",
        "description": "",
        "operationId": "detail_6",
        "parameters": [],
        "responses": {
          "200": {
            "description": "Successful response",
            "content": {
              "application/json": {
                "schema": {}
              }
            }
          }
        }
      }
    },
    "/v1/social/douyin/app/music/detail": {
      "post": {
        "summary": "detail",
        "description": "",
        "operationId": "detail_7",
        "parameters": [],
        "responses": {
          "200": {
            "description": "Successful response",
            "content": {
              "application/json": {
                "schema": {}
              }
            }
          }
        }
      }
    },
    "/v1/social/douyin/app/search/suggest_words": {
      "get": {
        "summary": "suggestWords",
        "description": "",
        "operationId": "suggestwords",
        "parameters": [
          {
            "name": "keyword",
            "in": "query",
            "required": false,
            "description": "Example value: anime",
            "schema": {
              "type": "string",
              "default": null,
              "enum": null
            }
          },
          {
            "name": "business_id",
            "in": "query",
            "required": false,
            "description": "Example value: 30003",
            "schema": {
              "type": "number",
              "default": "30003",
              "enum": null
            }
          },
          {
            "name": "from_group_id",
            "in": "query",
            "required": false,
            "description": "Example value: ",
            "schema": {
              "type": "string",
              "default": null,
              "enum": null
            }
          }
        ],
        "responses": {
          "200": {
            "description": "Successful response",
            "content": {
              "application/json": {
                "schema": {}
              }
            }
          }
        }
      }
    },
    "/v1/social/douyin/web/other/seo_inner_link": {
      "get": {
        "summary": "seoInnerLink",
        "description": "",
        "operationId": "seoinnerlink",
        "parameters": [],
        "responses": {
          "200": {
            "description": "Successful response",
            "content": {
              "application/json": {
                "schema": {}
              }
            }
          }
        }
      }
    }
  },
  "components": {
    "securitySchemes": {
      "ApiAuth": {
        "type": "apiKey",
        "in": "header",
        "name": "X-RapidAPI-Key"
      }
    }
  },
  "security": [
    {
      "ApiAuth": []
    }
  ]
}