{
  "openapi": "3.0.0",
  "info": {
    "title": "Realty In Au",
    "version": "1.0.0",
    "description": "RapidAPI: apidojo/realty-in-au"
  },
  "servers": [
    {
      "url": "https://realty-in-au.p.rapidapi.com"
    }
  ],
  "paths": {
    "/agents/get-listings": {
      "get": {
        "summary": "agents/get-listings",
        "description": "Get listings of an agent",
        "operationId": "agents/get_listings",
        "parameters": [
          {
            "name": "page",
            "in": "query",
            "required": false,
            "description": "For paging purpose",
            "schema": {
              "type": "number",
              "default": "1",
              "enum": null
            }
          },
          {
            "name": "channel",
            "in": "query",
            "required": false,
            "description": "One of the following : SOLD|BUY",
            "schema": {
              "type": "string",
              "default": null,
              "enum": null
            }
          },
          {
            "name": "linkedSalespeopleIds",
            "in": "query",
            "required": true,
            "description": "The values of linkedSalespeopleIds returned in .../agents/list endpoint. Separated by comma to accept multiple IDs",
            "schema": {
              "type": "string",
              "default": null,
              "enum": null
            }
          },
          {
            "name": "pageSize",
            "in": "query",
            "required": false,
            "description": "The number of items returned per page, for paging purpose",
            "schema": {
              "type": "number",
              "default": "20",
              "enum": null
            }
          }
        ],
        "responses": {
          "200": {
            "description": "Successful response",
            "content": {
              "application/json": {
                "schema": {}
              }
            }
          }
        }
      }
    },
    "/agency/get-listings": {
      "get": {
        "summary": "agency/get-listings",
        "description": "Get listings of an agency",
        "operationId": "agency/get_listings",
        "parameters": [
          {
            "name": "page",
            "in": "query",
            "required": false,
            "description": "For paging purpose",
            "schema": {
              "type": "number",
              "default": "1",
              "enum": null
            }
          },
          {
            "name": "channel",
            "in": "query",
            "required": false,
            "description": "One of the following : SOLD|BUY|RENT",
            "schema": {
              "type": "string",
              "default": null,
              "enum": null
            }
          },
          {
            "name": "agencyId",
            "in": "query",
            "required": true,
            "description": "The value of agencyId returned in .../agency/list endpoint",
            "schema": {
              "type": "string",
              "default": null,
              "enum": null
            }
          },
          {
            "name": "timeframe",
            "in": "query",
            "required": false,
            "description": "One of the following : -12|-9|-6|-3 (Only function with channel as SOLD)",
            "schema": {
              "type": "string",
              "default": null,
              "enum": null
            }
          },
          {
            "name": "pageSize",
            "in": "query",
            "required": false,
            "description": "The number of items returned per page, for paging purpose",
            "schema": {
              "type": "number",
              "default": "20",
              "enum": null
            }
          }
        ],
        "responses": {
          "200": {
            "description": "Successful response",
            "content": {
              "application/json": {
                "schema": {}
              }
            }
          }
        }
      }
    },
    "/agents/detail": {
      "get": {
        "summary": "agents/detail",
        "description": "Get agent detailed information",
        "operationId": "agents/detail",
        "parameters": [
          {
            "name": "id",
            "in": "query",
            "required": true,
            "description": "The value of id field returned in .../agents/list endpoint",
            "schema": {
              "type": "string",
              "default": null,
              "enum": null
            }
          }
        ],
        "responses": {
          "200": {
            "description": "Successful response",
            "content": {
              "application/json": {
                "schema": {}
              }
            }
          }
        }
      }
    },
    "/agency/detail": {
      "get": {
        "summary": "agency/detail",
        "description": "Get agency detailed information",
        "operationId": "agency/detail",
        "parameters": [
          {
            "name": "agencyId",
            "in": "query",
            "required": true,
            "description": "The value of agencyId returned in .../agency/list endpoint",
            "schema": {
              "type": "string",
              "default": null,
              "enum": null
            }
          }
        ],
        "responses": {
          "200": {
            "description": "Successful response",
            "content": {
              "application/json": {
                "schema": {}
              }
            }
          }
        }
      }
    },
    "/agents/list": {
      "get": {
        "summary": "agents/list",
        "description": "List agents with options and filters",
        "operationId": "agents/list",
        "parameters": [
          {
            "name": "page",
            "in": "query",
            "required": false,
            "description": "For paging purpose",
            "schema": {
              "type": "number",
              "default": "1",
              "enum": null
            }
          },
          {
            "name": "sortBy",
            "in": "query",
            "required": false,
            "description": "SUBURB_SALES_AND_PERFORMANCE|LEAD_PROPERTY_SALES|REVIEWS|MEDIAN_SALE_PRICE|MEDIAN_DAYS_ADVERTISED|YEARS_EXPERIENCE|TOTAL_SALES_ACROSS_ALL_SUBURBS",
            "schema": {
              "type": "string",
              "default": null,
              "enum": null
            }
          },
          {
            "name": "propertyType",
            "in": "query",
            "required": false,
            "description": "One of the following : ALL|HOUSE|UNIT_APARTMENT|LAND|TOWNHOUSE|RURAL|VILLA|ACREAGE|UNITBLOCK|RETIRE",
            "schema": {
              "type": "string",
              "default": null,
              "enum": null
            }
          },
          {
            "name": "suburbId",
            "in": "query",
            "required": true,
            "description": "The value of 'atlasId' returned in .../auto-complete endpoint. Ex : 7d1625e0-a6fd-420c-b969-572b5dbb5248 type field must be \\\"suburb\\\"",
            "schema": {
              "type": "string",
              "default": null,
              "enum": null
            }
          },
          {
            "name": "timeframe",
            "in": "query",
            "required": false,
            "description": "One of the following : -3|-6|-12|-24",
            "schema": {
              "type": "string",
              "default": null,
              "enum": null
            }
          },
          {
            "name": "hasRatingsReviewsToggle",
            "in": "query",
            "required": false,
            "description": "true|false",
            "schema": {
              "type": "string",
              "default": null,
              "enum": null
            }
          },
          {
            "name": "hasRatingsReviewsDisplayToggle",
            "in": "query",
            "required": false,
            "description": "true|false",
            "schema": {
              "type": "string",
              "default": null,
              "enum": null
            }
          }
        ],
        "responses": {
          "200": {
            "description": "Successful response",
            "content": {
              "application/json": {
                "schema": {}
              }
            }
          }
        }
      }
    },
    "/agency/list": {
      "get": {
        "summary": "agency/list",
        "description": "List agency with options and filters",
        "operationId": "agency/list",
        "parameters": [
          {
            "name": "page",
            "in": "query",
            "required": false,
            "description": "For paging purpose",
            "schema": {
              "type": "number",
              "default": "1",
              "enum": null
            }
          },
          {
            "name": "sort",
            "in": "query",
            "required": false,
            "description": "One of the following relevance|new-asc|new-desc|price-asc|price-desc|sold-relevance|sold-date-desc|sold-price-desc|sold-price-asc",
            "schema": {
              "type": "string",
              "default": null,
              "enum": null
            }
          },
          {
            "name": "channelType",
            "in": "query",
            "required": false,
            "description": "One of the following : BUY|RENT",
            "schema": {
              "type": "string",
              "default": null,
              "enum": null
            }
          },
          {
            "name": "locationType",
            "in": "query",
            "required": false,
            "description": "One of the following : OPERATING|SERVICING",
            "schema": {
              "type": "string",
              "default": null,
              "enum": null
            }
          },
          {
            "name": "suburb",
            "in": "query",
            "required": true,
            "description": "The value of 'display/text' returned in .../auto-complete endpoint. Spaces must be replaced with '-', removed comma if present, and in lower cases. Ex : Caulfield South, VIC 3162 -> caulfield-vic-3162 type field must be 'suburb'",
            "schema": {
              "type": "string",
              "default": null,
              "enum": null
            }
          }
        ],
        "responses": {
          "200": {
            "description": "Successful response",
            "content": {
              "application/json": {
                "schema": {}
              }
            }
          }
        }
      }
    },
    "/auto-complete": {
      "get": {
        "summary": "auto-complete",
        "description": "Get suggestions by term or phrase. The returned data will be used with .../properties/list endpoint",
        "operationId": "auto_complete",
        "parameters": [
          {
            "name": "query",
            "in": "query",
            "required": true,
            "description": "Any term or phrase you are familiar with. It can be an address to get the property id directly to use with .../properties/detail endpoint.",
            "schema": {
              "type": "string",
              "default": null,
              "enum": null
            }
          }
        ],
        "responses": {
          "200": {
            "description": "Successful response",
            "content": {
              "application/json": {
                "schema": {}
              }
            }
          }
        }
      }
    },
    "/schools/list": {
      "get": {
        "summary": "schools/list",
        "description": "List schools around a GEO location",
        "operationId": "schools/list",
        "parameters": [
          {
            "name": "lat",
            "in": "query",
            "required": true,
            "description": "The latitude of GEO location",
            "schema": {
              "type": "number",
              "default": "-37.79870933",
              "enum": null
            }
          },
          {
            "name": "lon",
            "in": "query",
            "required": true,
            "description": "The longitude of GEO location",
            "schema": {
              "type": "string",
              "default": null,
              "enum": null
            }
          }
        ],
        "responses": {
          "200": {
            "description": "Successful response",
            "content": {
              "application/json": {
                "schema": {}
              }
            }
          }
        }
      }
    },
    "/properties/lookup": {
      "get": {
        "summary": "properties/lookup (Deprecated)",
        "description": "Look for off-market property by id * Use .../properties/v2/lookup endpoint instead for more data returned.",
        "operationId": "properties/lookup_(deprecated)",
        "parameters": [
          {
            "name": "id",
            "in": "query",
            "required": true,
            "description": "The value of 'id' field returned in .../auto-complete endpoint with display as 'Property history'",
            "schema": {
              "type": "number",
              "default": "8270909",
              "enum": null
            }
          }
        ],
        "responses": {
          "200": {
            "description": "Successful response",
            "content": {
              "application/json": {
                "schema": {}
              }
            }
          }
        }
      }
    },
    "/properties/v3/lookup": {
      "get": {
        "summary": "properties/v3/lookup",
        "description": "Look for off-market property by id",
        "operationId": "properties/v3/lookup",
        "parameters": [
          {
            "name": "id",
            "in": "query",
            "required": true,
            "description": "The value of 'id' field returned in .../auto-complete endpoint with display as 'Property history'",
            "schema": {
              "type": "number",
              "default": "6041048",
              "enum": null
            }
          }
        ],
        "responses": {
          "200": {
            "description": "Successful response",
            "content": {
              "application/json": {
                "schema": {}
              }
            }
          }
        }
      }
    },
    "/properties/detail": {
      "get": {
        "summary": "properties/detail",
        "description": "Get detailed information of a property",
        "operationId": "properties/detail",
        "parameters": [
          {
            "name": "id",
            "in": "query",
            "required": true,
            "description": "The value of 'listingId' field returned in .../properties/list endpoint or 'id' field returned in .../auto-complete endpoint with type as listing",
            "schema": {
              "type": "number",
              "default": "0",
              "enum": null
            }
          }
        ],
        "responses": {
          "200": {
            "description": "Successful response",
            "content": {
              "application/json": {
                "schema": {}
              }
            }
          }
        }
      }
    },
    "/properties/list": {
      "get": {
        "summary": "properties/list",
        "description": "List properties with options and filters",
        "operationId": "properties/list",
        "parameters": [
          {
            "name": "page",
            "in": "query",
            "required": false,
            "description": "For paging purpose",
            "schema": {
              "type": "number",
              "default": "1",
              "enum": null
            }
          },
          {
            "name": "pageSize",
            "in": "query",
            "required": false,
            "description": "The number of items returned per response. For paging purpose (max is 30)",
            "schema": {
              "type": "number",
              "default": "30",
              "enum": null
            }
          },
          {
            "name": "sortType",
            "in": "query",
            "required": false,
            "description": "One of the following relevance|new-asc|new-desc|price-asc|price-desc|sold-relevance|sold-date-desc|sold-price-desc|sold-price-asc",
            "schema": {
              "type": "string",
              "default": null,
              "enum": null
            }
          },
          {
            "name": "channel",
            "in": "query",
            "required": true,
            "description": "One of the following : buy|rent|sold",
            "schema": {
              "type": "string",
              "default": null,
              "enum": null
            }
          },
          {
            "name": "propertyTypes",
            "in": "query",
            "required": false,
            "description": "Ignore or one of the following : townhouse|unit apartment|retire|acreage|land|unitblock|house|villa|rural. Separated by comma for multiple options. Ex : townhouse,house,villa",
            "schema": {
              "type": "string",
              "default": null,
              "enum": null
            }
          },
          {
            "name": "surroundingSuburbs",
            "in": "query",
            "required": false,
            "description": "Example value: ",
            "schema": {
              "type": "string",
              "default": null,
              "enum": null
            }
          },
          {
            "name": "searchLocation",
            "in": "query",
            "required": true,
            "description": "The value of text field returned in .../auto-complete endpoint",
            "schema": {
              "type": "string",
              "default": null,
              "enum": null
            }
          },
          {
            "name": "searchLocationSubtext",
            "in": "query",
            "required": true,
            "description": "The value of subtext field returned in .../auto-complete endpoint",
            "schema": {
              "type": "string",
              "default": null,
              "enum": null
            }
          },
          {
            "name": "type",
            "in": "query",
            "required": true,
            "description": "The value of region field returned in .../auto-complete endpoint",
            "schema": {
              "type": "string",
              "default": null,
              "enum": null
            }
          },
          {
            "name": "minimumBedrooms",
            "in": "query",
            "required": false,
            "description": "Example value: ",
            "schema": {
              "type": "number",
              "default": "0",
              "enum": null
            }
          },
          {
            "name": "maximumBedrooms",
            "in": "query",
            "required": false,
            "description": "Example value: ",
            "schema": {
              "type": "number",
              "default": "0",
              "enum": null
            }
          },
          {
            "name": "minimumLandSize",
            "in": "query",
            "required": false,
            "description": "In m2",
            "schema": {
              "type": "number",
              "default": "0",
              "enum": null
            }
          },
          {
            "name": "minimumBathroom",
            "in": "query",
            "required": false,
            "description": "Example value: ",
            "schema": {
              "type": "number",
              "default": "0",
              "enum": null
            }
          },
          {
            "name": "minimumCars",
            "in": "query",
            "required": false,
            "description": "Example value: ",
            "schema": {
              "type": "number",
              "default": "0",
              "enum": null
            }
          },
          {
            "name": "minimumPrice",
            "in": "query",
            "required": false,
            "description": "Example value: ",
            "schema": {
              "type": "number",
              "default": "0",
              "enum": null
            }
          },
          {
            "name": "maximumPrice",
            "in": "query",
            "required": false,
            "description": "Example value: ",
            "schema": {
              "type": "number",
              "default": "0",
              "enum": null
            }
          },
          {
            "name": "ex-under-contract",
            "in": "query",
            "required": false,
            "description": "Example value: ",
            "schema": {
              "type": "string",
              "default": null,
              "enum": null
            }
          },
          {
            "name": "constructionStatus",
            "in": "query",
            "required": false,
            "description": "Ignore or one of the following : established|new",
            "schema": {
              "type": "string",
              "default": null,
              "enum": null
            }
          },
          {
            "name": "keywords",
            "in": "query",
            "required": false,
            "description": "Facilities you are looking for. Separated by comma for multiple options. Ex : pool,garage,etc...",
            "schema": {
              "type": "string",
              "default": null,
              "enum": null
            }
          },
          {
            "name": "maxSoldAge",
            "in": "query",
            "required": false,
            "description": "Houses sold in the last x months",
            "schema": {
              "type": "number",
              "default": null,
              "enum": null
            }
          }
        ],
        "responses": {
          "200": {
            "description": "Successful response",
            "content": {
              "application/json": {
                "schema": {}
              }
            }
          }
        }
      }
    },
    "/properties/v2/lookup": {
      "get": {
        "summary": "properties/v2/lookup (Deprecated)",
        "description": "Look for off-market property by id",
        "operationId": "properties/v2/lookup_(deprecated)",
        "parameters": [
          {
            "name": "id",
            "in": "query",
            "required": true,
            "description": "The value of 'id' field returned in .../auto-complete endpoint with display as 'Property history'",
            "schema": {
              "type": "number",
              "default": "6041048",
              "enum": null
            }
          }
        ],
        "responses": {
          "200": {
            "description": "Successful response",
            "content": {
              "application/json": {
                "schema": {}
              }
            }
          }
        }
      }
    }
  },
  "components": {
    "securitySchemes": {
      "ApiAuth": {
        "type": "apiKey",
        "in": "header",
        "name": "X-RapidAPI-Key"
      }
    }
  },
  "security": [
    {
      "ApiAuth": []
    }
  ]
}